gem_utility/__init__.py
gem_utility/utility.py
gem_utility-0.0.1.dist-info/LICENSE
gem_utility-0.0.1.dist-info/METADATA
gem_utility-0.0.1.dist-info/WHEEL
gem_utility-0.0.1.dist-info/top_level.txt
gem_utility-0.0.1.dist-info/RECORD
